thermoML/__init__.py
thermoML/utils/Isothermal_base_model.py
thermoML/utils/Multitemperature_base_model.py
thermoML/utils/__init__.py
thermoML/utils/eval_model.py
thermoML/utils/hp_tuning.py
thermoml-0.1.0.dist-info/licenses/LICENSE
thermoml-0.1.0.dist-info/METADATA
thermoml-0.1.0.dist-info/WHEEL
thermoml-0.1.0.dist-info/top_level.txt
thermoml-0.1.0.dist-info/RECORD
